pomodoro_tracker/__init__.py
pomodoro_tracker/__main__.py
pomodoro_tracker/app.py
pomodoro_tracker/config.py
pomodoro_tracker/console.py
pomodoro_tracker/session.py
pomodoro_tracker/track.py
pomodoro_tracker/utils.py
pomodoro_tracker/writer.py
rudie_pomodoro_tracker-0.1.0.dist-info/LICENCE
rudie_pomodoro_tracker-0.1.0.dist-info/METADATA
rudie_pomodoro_tracker-0.1.0.dist-info/WHEEL
rudie_pomodoro_tracker-0.1.0.dist-info/entry_points.txt
rudie_pomodoro_tracker-0.1.0.dist-info/top_level.txt
rudie_pomodoro_tracker-0.1.0.dist-info/RECORD
