Metadata-Version: 2.1
Name: rudie-pomodoro-tracker
Version: 0.1.0
Summary: Pomodoro tracker with CLI interface.
Home-page: https://github.com/antibagr/pomodoro-tracker.git
Author: Anton Bagryanov
Author-email: rudiemeant@gmail.com
License: MIT
Platform: UNKNOWN
Classifier: License :: OSI Approved :: MIT License
Classifier: Programming Language :: Python :: 3
Classifier: Programming Language :: Python :: 3.9
